{"Activitybooked":{"schema":{"year":{"notNull":true,"maxLength":4,"verbose":"Year","type":"Integer"},"month":{"notNull":true,"maxLength":2,"verbose":"Month","type":"Integer"},"booked":{"null":true,"verbose":"Bookings","type":"Jsonb"},"activity":{"notNull":true,"maxLength":8,"verbose":"Activity","type":"Char"}},"constraints":{"fk":[{"name":"activity","columns":["activity"],"app":"avail","table":"Activity","tableColumns":["code"],"onDelete":"NO ACTION"}],"pk":["activity","year","month"]},"hidden":[],"dbschema":"","app":"avail","desc":"Activity Bookings","orderBy":["activity","year","month"]},"Actresbooked":{"schema":{"year":{"notNull":true,"maxLength":4,"verbose":"Year","type":"Integer"},"month":{"notNull":true,"maxLength":2,"verbose":"Month","type":"Integer"},"booked":{"null":true,"verbose":"Bookings","type":"Jsonb"},"actres":{"notNull":true,"maxLength":8,"verbose":"Activity Resource","type":"Char"}},"constraints":{"fk":[{"name":"actres","columns":["actres"],"app":"avail","table":"Actres","tableColumns":["code"],"onDelete":"NO ACTION"}],"pk":["actres","year","month"]},"hidden":[],"dbschema":"","app":"avail","desc":"Activity Resource Bookings","orderBy":["actres","year","month"]},"Actttotbooked":{"schema":{"year":{"notNull":true,"maxLength":4,"verbose":"Year","type":"Integer"},"month":{"notNull":true,"maxLength":2,"verbose":"Month","type":"Integer"},"booked":{"null":true,"verbose":"Bookings","type":"Jsonb"},"actttot":{"notNull":true,"maxLength":8,"verbose":"Activity Resource","type":"Char"}},"constraints":{"fk":[{"name":"actttot","columns":["actttot"],"app":"avail","table":"Actttot","tableColumns":["code"],"onDelete":"NO ACTION"}],"pk":["actttot","year","month"]},"hidden":[],"dbschema":"","app":"avail","desc":"Activity Time Total Bookings","orderBy":["actttot","year","month"]},"Lodgingbooked":{"schema":{"year":{"notNull":true,"maxLength":4,"verbose":"Year","type":"Integer"},"month":{"notNull":true,"maxLength":2,"verbose":"Month","type":"Integer"},"booked":{"null":true,"verbose":"Bookings","type":"Jsonb"},"lodging":{"notNull":true,"maxLength":8,"verbose":"Lodging","type":"Char"}},"constraints":{"fk":[{"name":"lodging","columns":["lodging"],"app":"avail","table":"Lodging","tableColumns":["code"],"onDelete":"NO ACTION"}],"pk":["lodging","year","month"]},"hidden":[],"dbschema":"","app":"avail","desc":"Lodging Bookings","orderBy":["lodging","year","month"]},"Mealbooked":{"schema":{"year":{"notNull":true,"maxLength":4,"verbose":"Year","type":"Integer"},"month":{"notNull":true,"maxLength":2,"verbose":"Month","type":"Integer"},"booked":{"null":true,"verbose":"Bookings","type":"Jsonb"},"meal":{"notNull":true,"maxLength":8,"verbose":"Meal","type":"Char"}},"constraints":{"fk":[{"name":"meal","columns":["meal"],"app":"avail","table":"Meals","tableColumns":["code"],"onDelete":"NO ACTION"}],"pk":["meal","year","month"]},"hidden":[],"dbschema":"","app":"avail","desc":"Meal Bookings","orderBy":["meal","year","month"]}}